pypi/__init__.py
OnlyTest-0.1.dist-info/LICENSE
OnlyTest-0.1.dist-info/METADATA
OnlyTest-0.1.dist-info/WHEEL
OnlyTest-0.1.dist-info/top_level.txt
OnlyTest-0.1.dist-info/RECORD
